{
  "version": "5",
  "dialect": "mysql",
  "id": "44572057-1bb6-4dad-995b-15c6acd5b8dc",
  "prevId": "e5e2d1d8-4c0e-462c-92a8-d0ac4a6db060",
  "tables": {
    "activity_logs": {
      "name": "activity_logs",
      "columns": {
        "id": {
          "name": "id",
          "type": "int",
          "primaryKey": false,
          "notNull": true,
          "autoincrement": true
        },
        "userId": {
          "name": "userId",
          "type": "int",
          "primaryKey": false,
          "notNull": false,
          "autoincrement": false
        },
        "action": {
          "name": "action",
          "type": "varchar(128)",
          "primaryKey": false,
          "notNull": true,
          "autoincrement": false
        },
        "entityType": {
          "name": "entityType",
          "type": "varchar(64)",
          "primaryKey": false,
          "notNull": false,
          "autoincrement": false
        },
        "entityId": {
          "name": "entityId",
          "type": "int",
          "primaryKey": false,
          "notNull": false,
          "autoincrement": false
        },
        "details": {
          "name": "details",
          "type": "text",
          "primaryKey": false,
          "notNull": false,
          "autoincrement": false
        },
        "ipAddress": {
          "name": "ipAddress",
          "type": "varchar(45)",
          "primaryKey": false,
          "notNull": false,
          "autoincrement": false
        },
        "createdAt": {
          "name": "createdAt",
          "type": "timestamp",
          "primaryKey": false,
          "notNull": true,
          "autoincrement": false,
          "default": "(now())"
        }
      },
      "indexes": {},
      "foreignKeys": {},
      "compositePrimaryKeys": {
        "activity_logs_id": {
          "name": "activity_logs_id",
          "columns": [
            "id"
          ]
        }
      },
      "uniqueConstraints": {},
      "checkConstraint": {}
    },
    "driver_profiles": {
      "name": "driver_profiles",
      "columns": {
        "id": {
          "name": "id",
          "type": "int",
          "primaryKey": false,
          "notNull": true,
          "autoincrement": true
        },
        "userId": {
          "name": "userId",
          "type": "int",
          "primaryKey": false,
          "notNull": true,
          "autoincrement": false
        },
        "licenseNumber": {
          "name": "licenseNumber",
          "type": "varchar(64)",
          "primaryKey": false,
          "notNull": false,
          "autoincrement": false
        },
        "vehicleType": {
          "name": "vehicleType",
          "type": "text",
          "primaryKey": false,
          "notNull": false,
          "autoincrement": false
        },
        "experienceYears": {
          "name": "experienceYears",
          "type": "int",
          "primaryKey": false,
          "notNull": false,
          "autoincrement": false
        },
        "rating": {
          "name": "rating",
          "type": "decimal(3,2)",
          "primaryKey": false,
          "notNull": false,
          "autoincrement": false,
          "default": "'0.00'"
        },
        "totalEarnings": {
          "name": "totalEarnings",
          "type": "decimal(10,2)",
          "primaryKey": false,
          "notNull": true,
          "autoincrement": false,
          "default": "'0.00'"
        },
        "completedOrders": {
          "name": "completedOrders",
          "type": "int",
          "primaryKey": false,
          "notNull": true,
          "autoincrement": false,
          "default": 0
        },
        "isAvailable": {
          "name": "isAvailable",
          "type": "boolean",
          "primaryKey": false,
          "notNull": true,
          "autoincrement": false,
          "default": true
        },
        "createdAt": {
          "name": "createdAt",
          "type": "timestamp",
          "primaryKey": false,
          "notNull": true,
          "autoincrement": false,
          "default": "(now())"
        },
        "updatedAt": {
          "name": "updatedAt",
          "type": "timestamp",
          "primaryKey": false,
          "notNull": true,
          "autoincrement": false,
          "onUpdate": true,
          "default": "(now())"
        }
      },
      "indexes": {},
      "foreignKeys": {},
      "compositePrimaryKeys": {
        "driver_profiles_id": {
          "name": "driver_profiles_id",
          "columns": [
            "id"
          ]
        }
      },
      "uniqueConstraints": {},
      "checkConstraint": {}
    },
    "orders": {
      "name": "orders",
      "columns": {
        "id": {
          "name": "id",
          "type": "int",
          "primaryKey": false,
          "notNull": true,
          "autoincrement": true
        },
        "clientId": {
          "name": "clientId",
          "type": "int",
          "primaryKey": false,
          "notNull": true,
          "autoincrement": false
        },
        "driverId": {
          "name": "driverId",
          "type": "int",
          "primaryKey": false,
          "notNull": false,
          "autoincrement": false
        },
        "vehicleType": {
          "name": "vehicleType",
          "type": "varchar(128)",
          "primaryKey": false,
          "notNull": true,
          "autoincrement": false
        },
        "vehicleMake": {
          "name": "vehicleMake",
          "type": "varchar(128)",
          "primaryKey": false,
          "notNull": false,
          "autoincrement": false
        },
        "vehicleModel": {
          "name": "vehicleModel",
          "type": "varchar(128)",
          "primaryKey": false,
          "notNull": false,
          "autoincrement": false
        },
        "pickupLocation": {
          "name": "pickupLocation",
          "type": "text",
          "primaryKey": false,
          "notNull": true,
          "autoincrement": false
        },
        "deliveryLocation": {
          "name": "deliveryLocation",
          "type": "text",
          "primaryKey": false,
          "notNull": true,
          "autoincrement": false
        },
        "pickupDate": {
          "name": "pickupDate",
          "type": "timestamp",
          "primaryKey": false,
          "notNull": true,
          "autoincrement": false
        },
        "deliveryDate": {
          "name": "deliveryDate",
          "type": "timestamp",
          "primaryKey": false,
          "notNull": false,
          "autoincrement": false
        },
        "status": {
          "name": "status",
          "type": "enum('erstellt','bestätigt','unterwegs','abgeschlossen','storniert')",
          "primaryKey": false,
          "notNull": true,
          "autoincrement": false,
          "default": "'erstellt'"
        },
        "totalPrice": {
          "name": "totalPrice",
          "type": "decimal(10,2)",
          "primaryKey": false,
          "notNull": true,
          "autoincrement": false
        },
        "insuranceFee": {
          "name": "insuranceFee",
          "type": "decimal(10,2)",
          "primaryKey": false,
          "notNull": true,
          "autoincrement": false
        },
        "systemCommission": {
          "name": "systemCommission",
          "type": "decimal(10,2)",
          "primaryKey": false,
          "notNull": true,
          "autoincrement": false
        },
        "driverPayout": {
          "name": "driverPayout",
          "type": "decimal(10,2)",
          "primaryKey": false,
          "notNull": true,
          "autoincrement": false
        },
        "notes": {
          "name": "notes",
          "type": "text",
          "primaryKey": false,
          "notNull": false,
          "autoincrement": false
        },
        "createdAt": {
          "name": "createdAt",
          "type": "timestamp",
          "primaryKey": false,
          "notNull": true,
          "autoincrement": false,
          "default": "(now())"
        },
        "updatedAt": {
          "name": "updatedAt",
          "type": "timestamp",
          "primaryKey": false,
          "notNull": true,
          "autoincrement": false,
          "onUpdate": true,
          "default": "(now())"
        }
      },
      "indexes": {},
      "foreignKeys": {},
      "compositePrimaryKeys": {
        "orders_id": {
          "name": "orders_id",
          "columns": [
            "id"
          ]
        }
      },
      "uniqueConstraints": {},
      "checkConstraint": {}
    },
    "payments": {
      "name": "payments",
      "columns": {
        "id": {
          "name": "id",
          "type": "int",
          "primaryKey": false,
          "notNull": true,
          "autoincrement": true
        },
        "orderId": {
          "name": "orderId",
          "type": "int",
          "primaryKey": false,
          "notNull": true,
          "autoincrement": false
        },
        "clientId": {
          "name": "clientId",
          "type": "int",
          "primaryKey": false,
          "notNull": true,
          "autoincrement": false
        },
        "amount": {
          "name": "amount",
          "type": "decimal(10,2)",
          "primaryKey": false,
          "notNull": true,
          "autoincrement": false
        },
        "paymentMethod": {
          "name": "paymentMethod",
          "type": "enum('stripe','paypal')",
          "primaryKey": false,
          "notNull": true,
          "autoincrement": false
        },
        "paymentStatus": {
          "name": "paymentStatus",
          "type": "enum('pending','completed','failed','refunded')",
          "primaryKey": false,
          "notNull": true,
          "autoincrement": false,
          "default": "'pending'"
        },
        "transactionId": {
          "name": "transactionId",
          "type": "varchar(255)",
          "primaryKey": false,
          "notNull": false,
          "autoincrement": false
        },
        "paymentIntentId": {
          "name": "paymentIntentId",
          "type": "varchar(255)",
          "primaryKey": false,
          "notNull": false,
          "autoincrement": false
        },
        "createdAt": {
          "name": "createdAt",
          "type": "timestamp",
          "primaryKey": false,
          "notNull": true,
          "autoincrement": false,
          "default": "(now())"
        },
        "updatedAt": {
          "name": "updatedAt",
          "type": "timestamp",
          "primaryKey": false,
          "notNull": true,
          "autoincrement": false,
          "onUpdate": true,
          "default": "(now())"
        }
      },
      "indexes": {},
      "foreignKeys": {},
      "compositePrimaryKeys": {
        "payments_id": {
          "name": "payments_id",
          "columns": [
            "id"
          ]
        }
      },
      "uniqueConstraints": {},
      "checkConstraint": {}
    },
    "payouts": {
      "name": "payouts",
      "columns": {
        "id": {
          "name": "id",
          "type": "int",
          "primaryKey": false,
          "notNull": true,
          "autoincrement": true
        },
        "orderId": {
          "name": "orderId",
          "type": "int",
          "primaryKey": false,
          "notNull": true,
          "autoincrement": false
        },
        "driverId": {
          "name": "driverId",
          "type": "int",
          "primaryKey": false,
          "notNull": true,
          "autoincrement": false
        },
        "amount": {
          "name": "amount",
          "type": "decimal(10,2)",
          "primaryKey": false,
          "notNull": true,
          "autoincrement": false
        },
        "payoutStatus": {
          "name": "payoutStatus",
          "type": "enum('pending','processing','completed','failed')",
          "primaryKey": false,
          "notNull": true,
          "autoincrement": false,
          "default": "'pending'"
        },
        "payoutMethod": {
          "name": "payoutMethod",
          "type": "varchar(64)",
          "primaryKey": false,
          "notNull": false,
          "autoincrement": false
        },
        "transactionId": {
          "name": "transactionId",
          "type": "varchar(255)",
          "primaryKey": false,
          "notNull": false,
          "autoincrement": false
        },
        "createdAt": {
          "name": "createdAt",
          "type": "timestamp",
          "primaryKey": false,
          "notNull": true,
          "autoincrement": false,
          "default": "(now())"
        },
        "updatedAt": {
          "name": "updatedAt",
          "type": "timestamp",
          "primaryKey": false,
          "notNull": true,
          "autoincrement": false,
          "onUpdate": true,
          "default": "(now())"
        }
      },
      "indexes": {},
      "foreignKeys": {},
      "compositePrimaryKeys": {
        "payouts_id": {
          "name": "payouts_id",
          "columns": [
            "id"
          ]
        }
      },
      "uniqueConstraints": {},
      "checkConstraint": {}
    },
    "system_config": {
      "name": "system_config",
      "columns": {
        "id": {
          "name": "id",
          "type": "int",
          "primaryKey": false,
          "notNull": true,
          "autoincrement": true
        },
        "configKey": {
          "name": "configKey",
          "type": "varchar(128)",
          "primaryKey": false,
          "notNull": true,
          "autoincrement": false
        },
        "configValue": {
          "name": "configValue",
          "type": "text",
          "primaryKey": false,
          "notNull": true,
          "autoincrement": false
        },
        "description": {
          "name": "description",
          "type": "text",
          "primaryKey": false,
          "notNull": false,
          "autoincrement": false
        },
        "updatedBy": {
          "name": "updatedBy",
          "type": "int",
          "primaryKey": false,
          "notNull": false,
          "autoincrement": false
        },
        "createdAt": {
          "name": "createdAt",
          "type": "timestamp",
          "primaryKey": false,
          "notNull": true,
          "autoincrement": false,
          "default": "(now())"
        },
        "updatedAt": {
          "name": "updatedAt",
          "type": "timestamp",
          "primaryKey": false,
          "notNull": true,
          "autoincrement": false,
          "onUpdate": true,
          "default": "(now())"
        }
      },
      "indexes": {},
      "foreignKeys": {},
      "compositePrimaryKeys": {
        "system_config_id": {
          "name": "system_config_id",
          "columns": [
            "id"
          ]
        }
      },
      "uniqueConstraints": {
        "system_config_configKey_unique": {
          "name": "system_config_configKey_unique",
          "columns": [
            "configKey"
          ]
        }
      },
      "checkConstraint": {}
    },
    "users": {
      "name": "users",
      "columns": {
        "id": {
          "name": "id",
          "type": "int",
          "primaryKey": false,
          "notNull": true,
          "autoincrement": true
        },
        "openId": {
          "name": "openId",
          "type": "varchar(64)",
          "primaryKey": false,
          "notNull": false,
          "autoincrement": false
        },
        "name": {
          "name": "name",
          "type": "text",
          "primaryKey": false,
          "notNull": true,
          "autoincrement": false
        },
        "email": {
          "name": "email",
          "type": "varchar(320)",
          "primaryKey": false,
          "notNull": false,
          "autoincrement": false
        },
        "username": {
          "name": "username",
          "type": "varchar(64)",
          "primaryKey": false,
          "notNull": false,
          "autoincrement": false
        },
        "passwordHash": {
          "name": "passwordHash",
          "type": "text",
          "primaryKey": false,
          "notNull": false,
          "autoincrement": false
        },
        "loginMethod": {
          "name": "loginMethod",
          "type": "varchar(64)",
          "primaryKey": false,
          "notNull": true,
          "autoincrement": false,
          "default": "'password'"
        },
        "role": {
          "name": "role",
          "type": "enum('super_admin','admin','client','driver')",
          "primaryKey": false,
          "notNull": true,
          "autoincrement": false,
          "default": "'client'"
        },
        "phone": {
          "name": "phone",
          "type": "varchar(32)",
          "primaryKey": false,
          "notNull": false,
          "autoincrement": false
        },
        "address": {
          "name": "address",
          "type": "text",
          "primaryKey": false,
          "notNull": false,
          "autoincrement": false
        },
        "createdAt": {
          "name": "createdAt",
          "type": "timestamp",
          "primaryKey": false,
          "notNull": true,
          "autoincrement": false,
          "default": "(now())"
        },
        "updatedAt": {
          "name": "updatedAt",
          "type": "timestamp",
          "primaryKey": false,
          "notNull": true,
          "autoincrement": false,
          "onUpdate": true,
          "default": "(now())"
        },
        "lastSignedIn": {
          "name": "lastSignedIn",
          "type": "timestamp",
          "primaryKey": false,
          "notNull": true,
          "autoincrement": false,
          "default": "(now())"
        }
      },
      "indexes": {},
      "foreignKeys": {},
      "compositePrimaryKeys": {
        "users_id": {
          "name": "users_id",
          "columns": [
            "id"
          ]
        }
      },
      "uniqueConstraints": {
        "users_openId_unique": {
          "name": "users_openId_unique",
          "columns": [
            "openId"
          ]
        },
        "users_email_unique": {
          "name": "users_email_unique",
          "columns": [
            "email"
          ]
        },
        "users_username_unique": {
          "name": "users_username_unique",
          "columns": [
            "username"
          ]
        }
      },
      "checkConstraint": {}
    }
  },
  "views": {},
  "_meta": {
    "schemas": {},
    "tables": {},
    "columns": {}
  },
  "internal": {
    "tables": {},
    "indexes": {}
  }
}